colboost/__init__.py
colboost/ensemble.py
colboost/py.typed
colboost/solvers/__init__.py
colboost/solvers/cg_boost.py
colboost/solvers/erlp_boost.py
colboost/solvers/lp_boost.py
colboost/solvers/md_boost.py
colboost/solvers/nm_boost.py
colboost/solvers/qrlp_boost.py
colboost/solvers/solver.py
colboost/utils/__init__.py
colboost/utils/predictions.py
colboost/utils/validate.py
colboost-0.1.5.dist-info/licenses/LICENSE
tests/conftest.py
tests/test_core_interface.py
tests/test_readme_examples.py
tests/test_solver_api.py
tests/test_solver_variants.py
tests/test_weight_reweighting.py
colboost-0.1.5.dist-info/METADATA
colboost-0.1.5.dist-info/WHEEL
colboost-0.1.5.dist-info/top_level.txt
colboost-0.1.5.dist-info/RECORD
